soroban/__init__.py
soroban/playground.ipynb
soroban/soroban.py
soroban_abacus-0.1.0.dist-info/METADATA
soroban_abacus-0.1.0.dist-info/WHEEL
soroban_abacus-0.1.0.dist-info/RECORD
